{
  "2025-07-10": "Client meeting at 11 AM",
  "2025-07-12": "Internal audit review",
  "2025-07-17": "Project deadline for Tax Filing",
  "2025-07-20": "Company offsite retreat",
  "2025-07-24": "GST submission reminder",
  "2025-07-28": "Legal compliance workshop",

  "2025-08-01": "Start of new financial quarter",
  "2025-08-05": "Income tax training session",
  "2025-08-10": "Meeting with CA partner",
  "2025-08-15": "Independence Day (Holiday)",
  "2025-08-21": "Finalize budget for Q3",
  "2025-08-25": "SEBI compliance checklist review",
  "2025-08-30": "Investor presentation dry run",

  "2025-09-03": "Payroll finalization",
  "2025-09-06": "Accounting software update",
  "2025-09-10": "Board meeting",
  "2025-09-13": "Client onboarding: ABC Ltd.",
  "2025-09-20": "Quarterly performance review",
  "2025-09-25": "ROC return filing deadline",
  "2025-09-28": "Team-building session",

  "2025-10-01": "Start planning Diwali gifts",
  "2025-10-05": "Vendor agreement review",
  "2025-10-10": "Digital transformation meeting",
  "2025-10-15": "Half-yearly tax filing",
  "2025-10-18": "Mid-month check-in with staff",
  "2025-10-22": "CA institute webinar",
  "2025-10-29": "Office maintenance day",

  "2025-11-02": "Budget planning kickoff",
  "2025-11-05": "Final CA trainee interviews",
  "2025-11-11": "Due diligence call with clients",
  "2025-11-15": "Tax saving investment discussion",
  "2025-11-20": "Income tax advance payment",
  "2025-11-25": "Year-end audit prep",
  "2025-11-30": "Monthly close meeting",

  "2025-12-03": "Christmas celebration planning",
  "2025-12-10": "Submit TDS return",
  "2025-12-15": "Annual strategy workshop",
  "2025-12-20": "HR feedback review",
  "2025-12-24": "Holiday party",
  "2025-12-31": "Year-end finance wrap-up"
}
